extraction/__init__.py
extraction/exceptions.py
extraction/py.typed
extraction/state.py
extraction/analyzers/__init__.py
extraction/analyzers/base.py
extraction/analyzers/catholic.py
extraction/analyzers/generic.py
extraction/builders/__init__.py
extraction/builders/epub_builder.py
extraction/cli/__init__.py
extraction/cli/extract.py
extraction/cli/scrape_images.py
extraction/cli/vatican_extract.py
extraction/core/__init__.py
extraction/core/chunking.py
extraction/core/extraction.py
extraction/core/identifiers.py
extraction/core/models.py
extraction/core/noise_filter.py
extraction/core/output.py
extraction/core/quality.py
extraction/core/strategies.py
extraction/core/text.py
extraction/extractors/__init__.py
extraction/extractors/base.py
extraction/extractors/configs.py
extraction/extractors/epub.py
extraction/extractors/epub.py.backup
extraction/extractors/html.py
extraction/extractors/json.py
extraction/extractors/markdown.py
extraction/extractors/pdf.py
extraction/pipelines/__init__.py
extraction/pipelines/vatican/__init__.py
extraction/pipelines/vatican/downloader.py
extraction/pipelines/vatican/index.py
extraction/pipelines/vatican/processor.py
extraction/pipelines/vatican/scraper.py
extraction/pipelines/vatican/storage.py
extraction/scrapers/__init__.py
extraction/scrapers/configs.py
extraction/scrapers/image_scraper.py
extraction/storage/__init__.py
extraction/storage/s3_uploader.py
extraction/tools/__init__.py
extraction/tools/overlap_strategies.py
extraction/tools/token_rechunker.py
extraction/tools/tokenizer_utils.py
doc_extraction-0.0.1.dist-info/METADATA
doc_extraction-0.0.1.dist-info/WHEEL
doc_extraction-0.0.1.dist-info/entry_points.txt
doc_extraction-0.0.1.dist-info/licenses/LICENSE
doc_extraction-0.0.1.dist-info/RECORD
