Metadata-Version: 2.4
Name: doc-extraction
Version: 0.0.1
Summary: Multi-format document extraction library for EPUB, PDF, HTML, Markdown, and JSON documents
Project-URL: Homepage, https://github.com/hello-world-bfree/extraction
Project-URL: Documentation, https://hello-world-bfree.github.io/extraction/
Project-URL: Repository, https://github.com/hello-world-bfree/extraction
Author-email: hello-world-bfree@pm.me
License: MIT
License-File: LICENSE
Keywords: chunking,document-processing,embeddings,epub,extraction,html,markdown,nlp,pdf,rag
Classifier: Development Status :: 3 - Alpha
Classifier: Intended Audience :: Developers
Classifier: Intended Audience :: Science/Research
Classifier: License :: OSI Approved :: MIT License
Classifier: Programming Language :: Python :: 3
Classifier: Programming Language :: Python :: 3.13
Classifier: Programming Language :: Python :: 3.14
Classifier: Topic :: Text Processing :: Linguistic
Classifier: Topic :: Text Processing :: Markup
Requires-Python: >=3.13
Requires-Dist: beautifulsoup4>=4.12.0
Requires-Dist: ebooklib>=0.18
Requires-Dist: lxml>=4.9.0
Requires-Dist: requests>=2.31.0
Requires-Dist: tqdm>=4.66.0
Provides-Extra: dev
Requires-Dist: pytest-asyncio>=0.21.0; extra == 'dev'
Requires-Dist: pytest-cov>=4.1.0; extra == 'dev'
Requires-Dist: pytest-mock>=3.11.0; extra == 'dev'
Requires-Dist: pytest>=7.4.0; extra == 'dev'
Provides-Extra: epub-images
Requires-Dist: pillow>=10.0.0; extra == 'epub-images'
Provides-Extra: finetuning
Requires-Dist: sentencepiece>=0.1.99; extra == 'finetuning'
Requires-Dist: torch>=2.1.0; extra == 'finetuning'
Requires-Dist: transformers>=4.36.0; extra == 'finetuning'
Provides-Extra: images
Requires-Dist: extraction[epub-images,s3,scraping]; extra == 'images'
Provides-Extra: pdf
Requires-Dist: pdfplumber>=0.10.0; extra == 'pdf'
Provides-Extra: s3
Requires-Dist: boto3>=1.34.0; extra == 's3'
Provides-Extra: scraping
Requires-Dist: pillow>=10.0.0; extra == 'scraping'
Requires-Dist: playwright>=1.42.0; extra == 'scraping'
Provides-Extra: vatican
Requires-Dist: boto3>=1.28.0; extra == 'vatican'
Requires-Dist: botocore>=1.31.0; extra == 'vatican'
